README
setup.py
mongotron/Collection.py
mongotron/ConnectionManager.py
mongotron/Cursor.py
mongotron/Database.py
mongotron/Document.py
mongotron/SequenceGenerator.py
mongotron/__init__.py
mongotron/exceptions.py
mongotron/field_types.py
mongotron/wrapped_types.py
mongotron.egg-info/PKG-INFO
mongotron.egg-info/SOURCES.txt
mongotron.egg-info/dependency_links.txt
mongotron.egg-info/not-zip-safe
mongotron.egg-info/requires.txt
mongotron.egg-info/top_level.txt