Metadata-Version: 1.0
Name: mongotron
Version: 0.3
Summary: Python mongodb ODM
Home-page: http://www.github.com/narrato/mongotron
Author: Tony Million
Author-email: tony@narrato.co
License: MIT License
Platform: UNKNOWN
Classifier: Development Status :: 3 - Alpha
Classifier: Environment :: Other Environment
Classifier: Intended Audience :: Developers
Classifier: License :: OSI Approved :: MIT License
Classifier: Operating System :: OS Independent
Classifier: Programming Language :: Python
Classifier: Topic :: Database
Classifier: Topic :: Utilities
Classifier: Topic :: Software Development :: Libraries :: Python Modules
